mina/__init__.py
mina/mina.py
minaotp-1.0.8.dist-info/DESCRIPTION.rst
minaotp-1.0.8.dist-info/METADATA
minaotp-1.0.8.dist-info/RECORD
minaotp-1.0.8.dist-info/WHEEL
minaotp-1.0.8.dist-info/entry_points.txt
minaotp-1.0.8.dist-info/metadata.json
minaotp-1.0.8.dist-info/top_level.txt
