Metadata-Version: 2.0
Name: minaotp
Version: 1.0.8
Summary: TOTP authenticator implement as a terminal tool
Home-page: https://github.com/MinaOTP/MinaOTP-Shell
Author: lancegin
Author-email: gin.lance.inside@hotmail.com
License: MIT
Keywords: authenticator,totp,rfc-6238,command-line-tool
Platform: UNKNOWN
Classifier: Development Status :: 5 - Production/Stable
Classifier: Intended Audience :: Developers
Classifier: Topic :: Software Development :: Libraries :: Python Modules
Classifier: License :: OSI Approved :: MIT License
Classifier: Programming Language :: Python :: 3 :: Only
Requires-Dist: pyotp
